[{"id":"r1","name":"Manaki","address":"Prilepska","cuisine":"Macedonian","website":"https://nemasite.com","description":"Palacinka"},{"id":"r2","name":"Kapri","address":"Dihovo bb 55","cuisine":"Macedonian","website":"https://kapri.mk","description":"Awesome!"},{"id":"r3","name":"Restaurant 3","address":"pril","cuisine":"Maced","website":"https://www.gome.com","description":"WHY"},{"id":"r4","name":"aaaa","address":"llll","cuisine":"llll","website":"https://www.nema.com","description":"kk"},{"name":"Aurum","address":"Aurum br.55","cuisine":"Macedonian","website":"https://www.aurum.com","description":"Good","id":"6e93c28e-b3aa-4b1a-8cb0-a4bfcdda73cf"},{"name":"Bure","address":"Partizanska broj55","cuisine":"Macedonian","website":"https://www.bure.mk","description":"Awesome!!!","id":"eaaef2be-c018-4c41-85db-2532465625aa"}]